odoo/addons/web_decimal_numpad_dot/README.rst
odoo/addons/web_decimal_numpad_dot/__init__.py
odoo/addons/web_decimal_numpad_dot/__manifest__.py
odoo/addons/web_decimal_numpad_dot/i18n/es.po
odoo/addons/web_decimal_numpad_dot/i18n/it.po
odoo/addons/web_decimal_numpad_dot/i18n/web_decimal_numpad_dot.pot
odoo/addons/web_decimal_numpad_dot/i18n/zh_CN.po
odoo/addons/web_decimal_numpad_dot/readme/CONTRIBUTORS.rst
odoo/addons/web_decimal_numpad_dot/readme/DESCRIPTION.rst
odoo/addons/web_decimal_numpad_dot/readme/USAGE.rst
odoo/addons/web_decimal_numpad_dot/static/description/icon.png
odoo/addons/web_decimal_numpad_dot/static/description/index.html
odoo/addons/web_decimal_numpad_dot/static/src/js/numpad_dot.js
odoo/addons/web_decimal_numpad_dot/views/web_decimal_numpad_dot.xml
odoo14_addon_web_decimal_numpad_dot-14.0.1.0.1.dev5.dist-info/METADATA
odoo14_addon_web_decimal_numpad_dot-14.0.1.0.1.dev5.dist-info/WHEEL
odoo14_addon_web_decimal_numpad_dot-14.0.1.0.1.dev5.dist-info/top_level.txt
odoo14_addon_web_decimal_numpad_dot-14.0.1.0.1.dev5.dist-info/RECORD
